aws_ninja/__init__.py
aws_ninja/cli.py
aws_ninja/commands/__init__.py
aws_ninja/commands/recommendations.py
aws_ninja/templates/recommendations/recommendations.html.jinja
aws_ninja/templates/recommendations/recommendations_ecs.html.jinja
aws_ninja/templates/recommendations/recommendations_rds.html.jinja
aws_ninja/templates/recommendations/recommendations_trusted_advisor.html.jinja
aws_ninja/templates/resource_tags.html.jinja
aws_ninja/utils/__init__.py
aws_ninja/utils/aws/__init__.py
aws_ninja/utils/aws/compute_optimizer/__init__.py
aws_ninja/utils/aws/compute_optimizer/ecs.py
aws_ninja/utils/aws/compute_optimizer/rds.py
aws_ninja/utils/aws/container_insights/__init__.py
aws_ninja/utils/aws/trim_arn.py
aws_ninja/utils/aws/trusted_advisor.py
aws_ninja-0.2.1.dist-info/METADATA
aws_ninja-0.2.1.dist-info/WHEEL
aws_ninja-0.2.1.dist-info/entry_points.txt
aws_ninja-0.2.1.dist-info/RECORD
