Metadata-Version: 2.3
Name: aws-ninja
Version: 0.2.1
Summary: A collection of tools to use when reviewing AWS accounts and their setup.
Author: Lawrence
Author-email: lawrence@acode.ninja
Requires-Python: >=3.12,<4.0
Classifier: Programming Language :: Python :: 3
Classifier: Programming Language :: Python :: 3.12
Classifier: Programming Language :: Python :: 3.13
Requires-Dist: boto3 (>=1.34.148,<2.0.0)
Requires-Dist: cement (>=3.0.10,<4.0.0)
Requires-Dist: click (>=8.1.7,<9.0.0)
Requires-Dist: jinja2 (>=3.1.4,<4.0.0)
Requires-Dist: jsonpickle (>=3.2.2,<4.0.0)
